winiutils/__init__.py
winiutils/dev/__init__.py
winiutils/dev/builders/__init__.py
winiutils/dev/cli/__init__.py
winiutils/dev/cli/shared_subcommands.py
winiutils/dev/cli/subcommands.py
winiutils/dev/configs/__init__.py
winiutils/dev/management/__init__.py
winiutils/dev/tests/__init__.py
winiutils/dev/tests/fixtures/__init__.py
winiutils/dev/tests/fixtures/fixtures.py
winiutils/main.py
winiutils/py.typed
winiutils/resources/__init__.py
winiutils/src/__init__.py
winiutils/src/data/__init__.py
winiutils/src/data/dataframe/__init__.py
winiutils/src/data/dataframe/cleaning.py
winiutils/src/data/structures/__init__.py
winiutils/src/data/structures/dicts.py
winiutils/src/data/structures/text/__init__.py
winiutils/src/data/structures/text/string_.py
winiutils/src/iterating/__init__.py
winiutils/src/iterating/concurrent/__init__.py
winiutils/src/iterating/concurrent/concurrent.py
winiutils/src/iterating/concurrent/multiprocessing.py
winiutils/src/iterating/concurrent/multithreading.py
winiutils/src/iterating/iterate.py
winiutils/src/oop/__init__.py
winiutils/src/oop/mixins/__init__.py
winiutils/src/oop/mixins/meta.py
winiutils/src/oop/mixins/mixin.py
winiutils/src/security/__init__.py
winiutils/src/security/cryptography.py
winiutils/src/security/keyring.py
winiutils-2.3.52.dist-info/licenses/LICENSE
winiutils-2.3.52.dist-info/WHEEL
winiutils-2.3.52.dist-info/entry_points.txt
winiutils-2.3.52.dist-info/METADATA
winiutils-2.3.52.dist-info/RECORD
