Metadata-Version: 2.4
Name: winiutils
Version: 2.3.52
Summary: A utility library for Python development
Keywords: 
Author: Winipedia
License-Expression: MIT
License-File: LICENSE
Classifier: Programming Language :: Python :: 3.12
Classifier: Programming Language :: Python :: 3.13
Classifier: Programming Language :: Python :: 3.14
Classifier: Operating System :: OS Independent
Classifier: Typing :: Typed
Requires-Dist: cryptography
Requires-Dist: defusedxml
Requires-Dist: keyring
Requires-Dist: keyrings-alt
Requires-Dist: polars
Requires-Dist: pyrig
Requires-Dist: tqdm
Maintainer: Winipedia
Requires-Python: >=3.12
Project-URL: Changelog, https://github.com/Winipedia/winiutils/releases
Project-URL: Documentation, https://Winipedia.github.io/winiutils
Project-URL: Homepage, https://github.com/Winipedia/winiutils
Project-URL: Issues, https://github.com/Winipedia/winiutils/issues
Project-URL: Source, https://github.com/Winipedia/winiutils
